{"archives": {"2024": []}, "categories": {"Hacking": []}, "tags": {"programming": []}, "articleDatas": [{"title": "Useful Hacking Commands", "description": "\u4e00\u4e9b\u6709\u53ef\u80fd\u7528\u7684\u6307\u4ee4", "category": "Hacking", "tags": ["programming"], "publishedTime": "2024/10/16", "cover": "custom_alanwu/image/articleCover/Useful_Hacking_Command_cover.png", "name": "UsefulHackingCommands", "path": "custom_alanwu\\article\\UsefulHackingCommands.md", "readingTime": "1 minute", "archive": "2024"}, {"title": "Pwnagotchi", "description": "Pwnagotchi \u7c21\u6613\u914d\u7f6e\u6559\u5b78 zh-tw", "category": "Hacking", "tags": ["programming"], "publishedTime": "2024/10/18", "cover": "custom_alanwu/image/articleCover/pwnagotchi_cover.gif", "name": "Pwnaogtchi", "path": "custom_alanwu\\article\\Pwnaogtchi.md", "readingTime": "5 minute", "archive": "2024"}]}